waveshare_epd/__init__.py
waveshare_epd/epd13in3b.py
waveshare_epd/epd13in3k.py
waveshare_epd/epd1in02.py
waveshare_epd/epd1in54.py
waveshare_epd/epd1in54_V2.py
waveshare_epd/epd1in54b.py
waveshare_epd/epd1in54b_V2.py
waveshare_epd/epd1in54c.py
waveshare_epd/epd1in64g.py
waveshare_epd/epd2in13.py
waveshare_epd/epd2in13_V2.py
waveshare_epd/epd2in13_V3.py
waveshare_epd/epd2in13_V4.py
waveshare_epd/epd2in13b_V3.py
waveshare_epd/epd2in13b_V4.py
waveshare_epd/epd2in13bc.py
waveshare_epd/epd2in13d.py
waveshare_epd/epd2in13g.py
waveshare_epd/epd2in15b.py
waveshare_epd/epd2in15g.py
waveshare_epd/epd2in36g.py
waveshare_epd/epd2in66.py
waveshare_epd/epd2in66b.py
waveshare_epd/epd2in66g.py
waveshare_epd/epd2in7.py
waveshare_epd/epd2in7_V2.py
waveshare_epd/epd2in7b.py
waveshare_epd/epd2in7b_V2.py
waveshare_epd/epd2in9.py
waveshare_epd/epd2in9_V2.py
waveshare_epd/epd2in9b_V3.py
waveshare_epd/epd2in9b_V4.py
waveshare_epd/epd2in9bc.py
waveshare_epd/epd2in9d.py
waveshare_epd/epd3in0g.py
waveshare_epd/epd3in52.py
waveshare_epd/epd3in7.py
waveshare_epd/epd4in01f.py
waveshare_epd/epd4in2.py
waveshare_epd/epd4in26.py
waveshare_epd/epd4in2_V2.py
waveshare_epd/epd4in2b_V2.py
waveshare_epd/epd4in2b_V2_old.py
waveshare_epd/epd4in2bc.py
waveshare_epd/epd4in37g.py
waveshare_epd/epd5in65f.py
waveshare_epd/epd5in79.py
waveshare_epd/epd5in79b.py
waveshare_epd/epd5in79g.py
waveshare_epd/epd5in83.py
waveshare_epd/epd5in83_V2.py
waveshare_epd/epd5in83b_V2.py
waveshare_epd/epd5in83bc.py
waveshare_epd/epd7in3e.py
waveshare_epd/epd7in3f.py
waveshare_epd/epd7in3g.py
waveshare_epd/epd7in5.py
waveshare_epd/epd7in5_HD.py
waveshare_epd/epd7in5_V2.py
waveshare_epd/epd7in5_V2_old.py
waveshare_epd/epd7in5b_HD.py
waveshare_epd/epd7in5b_V2.py
waveshare_epd/epd7in5b_V2_old.py
waveshare_epd/epd7in5bc.py
waveshare_epd/epdconfig.py
eink_wave-0.1.0.dist-info/METADATA
eink_wave-0.1.0.dist-info/WHEEL
eink_wave-0.1.0.dist-info/RECORD
