Metadata-Version: 2.4
Name: eink-wave
Version: 0.1.0
Summary: Modernized Waveshare e-Paper library using python-periphery and uv
Requires-Python: >=3.8.1
Requires-Dist: pillow>=9.0.0
Requires-Dist: python-periphery>=2.4.0
